phlite_grpph-0.1.1.dist-info/METADATA
phlite_grpph-0.1.1.dist-info/WHEEL
phlite_grpph/__init__.py
phlite_grpph/phlite_grpph.cpython-312-darwin.so
phlite_grpph-0.1.1.dist-info/RECORD
